esat_rust.cpython-310-x86_64-linux-gnu.so
esat/estimator.py
esat/main.py
esat/configs.py
esat/__init__.py
esat/metrics.py
esat/utils.py
esat/model/batch_sa.py
esat/model/sa.py
esat/model/__init__.py
esat/model/ls_nmf.py
esat/model/recombinator.py
esat/model/ws_nmf.py
esat/cli/__init__.py
esat/cli/esat_cli.py
esat/data/datahandler.py
esat/data/test_tools.py
esat/data/__init__.py
esat/data/analysis.py
esat/error/bootstrap.py
esat/error/displacement.py
esat/error/__init__.py
esat/error/bs_disp.py
esat/error/error.py
esat/rotational/constrained.py
esat/rotational/__init__.py
esat_eval/runtime_test.py
esat_eval/profile_compare_test.py
esat_eval/simulator.py
esat_eval/rust_optimizations_test.py
esat_eval/perturbation.py
esat_eval/factor_comparison.py
esat_eval/__init__.py
esat_eval/rust_functions_test.py
esat_eval/factor_catalog.py
esat_eval/loss_value_test.py
esat.libs/libgcc_s-a0b57c20.so.1
esat-2025.0.1.dist-info/WHEEL
esat-2025.0.1.dist-info/top_level.txt
esat-2025.0.1.dist-info/entry_points.txt
esat-2025.0.1.dist-info/RECORD
esat-2025.0.1.dist-info/METADATA
esat-2025.0.1.dist-info/licenses/LICENSE
