Metadata-Version: 2.4
Name: esat
Version: 2025.0.1
Summary: EPA's Environmental Source Apportionment Toolkit python package.
Author-email: Deron Smith <smith.deron@epa.gov>, Mike Cyterski <cyterski.mike@epa.gov>
Maintainer-email: Deron Smith <smith.deron@epa.gov>
License-Expression: Apache-2.0
Project-URL: Documentation, https://quanted.github.io/esat/
Project-URL: Repository, https://github.com/quanted/esat.git
Project-URL: Issues, https://github.com/quanted/esat/issues
Classifier: Development Status :: 3 - Alpha
Classifier: Programming Language :: Python
Classifier: Programming Language :: Rust
Classifier: Programming Language :: Python :: Implementation :: CPython
Classifier: Programming Language :: Python :: Implementation :: PyPy
Requires-Python: >=3.10
License-File: LICENSE
Requires-Dist: click==8.2.1
Requires-Dist: numba==0.61.2
Requires-Dist: numpy==2.2.6
Requires-Dist: pandas[excel,performance]==2.3.0
Requires-Dist: plotly==6.1.2
Requires-Dist: psutil==7.0.0
Requires-Dist: scipy==1.15.3
Requires-Dist: tabulate==0.9.0
Requires-Dist: tqdm==4.67.1
Requires-Dist: typer==0.16.0
Dynamic: license-file
